wtm/__init__.py
wtm/_wtm.py
wtm/lib.py
wtm/loggers.py
wtm/utils.py
wtm-1.0.2.data/scripts/wtm
wtm-1.0.2.dist-info/LICENSE
wtm-1.0.2.dist-info/METADATA
wtm-1.0.2.dist-info/WHEEL
wtm-1.0.2.dist-info/top_level.txt
wtm-1.0.2.dist-info/RECORD
