Metadata-Version: 2.1
Name: wtm
Version: 1.0.2
Summary: Downloads songs from the internet.
Home-page: https://github.com/mentix02/wtm
Author: manan
Author-email: manan.yadav02@gmail.com
License: MIT
Keywords: wtm what-the-music music what the music
Platform: UNKNOWN
Classifier: Topic :: Multimedia :: Sound/Audio
Classifier: Programming Language :: Python :: 3
Requires-Dist: bs4
Requires-Dist: eyeD3
Requires-Dist: requests
Requires-Dist: youtube-dl
Requires-Dist: prettytable
